ema/HCN1-variants-example.ipynb
ema/__init__.py
ema/ema.py
ema/ema_example.ipynb
ema/ion-channel-proteins-example.ipynb
ema/test.py
ema_emb-0.0.5.dist-info/METADATA
ema_emb-0.0.5.dist-info/WHEEL
ema_emb-0.0.5.dist-info/licenses/LICENSE
ema_emb-0.0.5.dist-info/RECORD
