Metadata-Version: 2.3
Name: ema-emb
Version: 0.0.5
Summary: A library for comparing embedding spaces
Project-URL: Homepage, https://github.com/pia-francesca/ema
Project-URL: Issues, https://github.com/pia-francesca/ema/issues
Author-email: Francesca Rissom <francesca.rissom@hpi.de>, Paulo Yanez Sarmiento <paul.yanze@hpi.de>, Jordan Safer <jsafer@broadinstitute.org>
License-File: LICENSE
Classifier: License :: OSI Approved :: MIT License
Classifier: Operating System :: OS Independent
Classifier: Programming Language :: Python :: 3
Requires-Python: >=3.9
Requires-Dist: numpy==1.24.4
Requires-Dist: pandas==2.0.3
Requires-Dist: plotly==5.21.0
Requires-Dist: scikit-learn==1.3.2
Requires-Dist: scipy==1.13.1
Requires-Dist: umap-learn==0.5.6
